rtl/uart_tx.v
`timescale 1ns/1ps

module uart_tx(
    input baud_tick, rst_n, clk, tx_start,
    input [7:0]data, 
    output reg tx , tx_busy
);

reg [1:0]state;
reg [2:0] bit_index = 3'd0;
reg [7:0] data_reg;

localparam IDLE  = 2'd0;
localparam START = 2'd1;
localparam DATA  = 2'd2;
localparam STOP  = 2'd3;

always @(posedge clk or negedge rst_n)
begin
    if(!rst_n)
    begin
        state <= IDLE;
        bit_index <= 3'd0;
        tx <= 1'd1;
        tx_busy <= 1'd0;
    end
    else
    begin
        if(baud_tick)
        begin
            case (state)
                IDLE : begin
                            tx <= 1'd1;
                            tx_busy <= 1'd0;
                            if(tx_start)
                                state <= START;
                end 
                START : begin
                            tx <= 1'd0;
                            tx_busy <= 1'd1;
                            state <= DATA;
                            bit_index <= 3'd0;
                            data_reg <= data;
                end
                DATA : begin
                            tx <= data_reg[bit_index];
                            
                            if (bit_index == 3'd7)  
                                begin
                                    state <= STOP;
                                    bit_index <= 3'd0;
                                end
                            else
                                bit_index <= bit_index + 3'd1;
                end
                STOP : begin
                            tx <= 1'd1;
                            state <= IDLE;
                            tx_busy <= 1'd0;
                end
                default: begin
                            state <= IDLE;
                            tx <= 1'b1;
                end
            endcase
        end
    end
end


endmodule

testbenches/uart_tx_tb.v
`timescale 1ns/1ps

module uart_tx_tb;

reg clk;
reg rst_n;
reg baud_tick;
reg tx_start;

reg [7:0] data;

wire tx;
wire tx_busy;

uart_tx DUT(
    .clk(clk),
    .rst_n(rst_n),
    .baud_tick(baud_tick),
    .tx_start(tx_start),
    .data(data),
    .tx(tx),
    .tx_busy(tx_busy)
);

always #10 clk = ~clk;

always begin
    baud_tick = 0;
    #1000;
    baud_tick = 1;
    #20;
end


initial begin

    clk = 0;
    rst_n = 0;
    tx_start = 0;
    data = 8'h00;

    #50;
    rst_n = 1;

  #2000;
    data = 8'hA5;
    tx_start = 1;
   
    #30000;
    tx_start = 0;
    $finish;

end

initial begin
    $dumpfile("uart_tx.vcd");
    $dumpvars(0, uart_tx_tb);
end
endmodule

docs/waveforms/uart_tx.vcd
$date
	Sun May 10 17:41:08 2026
$end
$version
	Icarus Verilog
$end
$timescale
	1ps
$end
$scope module uart_tx_tb $end
$var wire 1 ! tx_busy $end
$var wire 1 " tx $end
$var reg 1 # baud_tick $end
$var reg 1 $ clk $end
$var reg 8 % data [7:0] $end
$var reg 1 & rst_n $end
$var reg 1 ' tx_start $end
$scope module DUT $end
$var wire 1 # baud_tick $end
$var wire 1 $ clk $end
$var wire 8 ( data [7:0] $end
$var wire 1 & rst_n $end
$var wire 1 ' tx_start $end
$var reg 3 ) bit_index [2:0] $end
$var reg 8 * data_reg [7:0] $end
$var reg 2 + state [1:0] $end
$var reg 1 " tx $end
$var reg 1 ! tx_busy $end
$upscope $end
$upscope $end
$enddefinitions $end
$comment Show the parameter values. $end
$dumpall
$end
#0
$dumpvars
b0 +
bx *
b0 )
b0 (
0'
0&
b0 %
0$
0#
1"
0!
$end
#10000
1$
#20000
0$
#30000
1$
#40000
0$
#50000
1$
1&
#60000
0$
#70000
1$
#80000
0$
#90000
1$
#100000
0$
#110000
1$
#120000
0$
#130000
1$
#140000
0$
#150000
1$
#160000
0$
#170000
1$
#180000
0$
#190000
1$
#200000
0$
#210000
1$
#220000
0$
#230000
1$
#240000
0$
#250000
1$
#260000
0$
#270000
1$
#280000
0$
#290000
1$
#300000
0$
#310000
1$
#320000
0$
#330000
1$
#340000
0$
#350000
1$
#360000
0$
#370000
1$
#380000
0$
#390000
1$
#400000
0$
#410000
1$
#420000
0$
#430000
1$
#440000
0$
#450000
1$
#460000
0$
#470000
1$
#480000
0$
#490000
1$
#500000
0$
#510000
1$
#520000
0$
#530000
1$
#540000
0$
#550000
1$
#560000
0$
#570000
1$
#580000
0$
#590000
1$
#600000
0$
#610000
1$
#620000
0$
#630000
1$
#640000
0$
#650000
1$
#660000
0$
#670000
1$
#680000
0$
#690000
1$
#700000
0$
#710000
1$
#720000
0$
#730000
1$
#740000
0$
#750000
1$
#760000
0$
#770000
1$
#780000
0$
#790000
1$
#800000
0$
#810000
1$
#820000
0$
#830000
1$
#840000
0$
#850000
1$
#860000
0$
#870000
1$
#880000
0$
#890000
1$
#900000
0$
#910000
1$
#920000
0$
#930000
1$
#940000
0$
#950000
1$
#960000
0$
#970000
1$
#980000
0$
#990000
1$
#1000000
0$
1#
#1010000
1$
#1020000
0$
0#
#1030000
1$
#1040000
0$
#1050000
1$
#1060000
0$
#1070000
1$
#1080000
0$
#1090000
1$
#1100000
0$
#1110000
1$
#1120000
0$
#1130000
1$
#1140000
0$
#1150000
1$
#1160000
0$
#1170000
1$
#1180000
0$
#1190000
1$
#1200000
0$
#1210000
1$
#1220000
0$
#1230000
1$
#1240000
0$
#1250000
1$
#1260000
0$
#1270000
1$
#1280000
0$
#1290000
1$
#1300000
0$
#1310000
1$
#1320000
0$
#1330000
1$
#1340000
0$
#1350000
1$
#1360000
0$
#1370000
1$
#1380000
0$
#1390000
1$
#1400000
0$
#1410000
1$
#1420000
0$
#1430000
1$
#1440000
0$
#1450000
1$
#1460000
0$
#1470000
1$
#1480000
0$
#1490000
1$
#1500000
0$
#1510000
1$
#1520000
0$
#1530000
1$
#1540000
0$
#1550000
1$
#1560000
0$
#1570000
1$
#1580000
0$
#1590000
1$
#1600000
0$
#1610000
1$
#1620000
0$
#1630000
1$
#1640000
0$
#1650000
1$
#1660000
0$
#1670000
1$
#1680000
0$
#1690000
1$
#1700000
0$
#1710000
1$
#1720000
0$
#1730000
1$
#1740000
0$
#1750000
1$
#1760000
0$
#1770000
1$
#1780000
0$
#1790000
1$
#1800000
0$
#1810000
1$
#1820000
0$
#1830000
1$
#1840000
0$
#1850000
1$
#1860000
0$
#1870000
1$
#1880000
0$
#1890000
1$
#1900000
0$
#1910000
1$
#1920000
0$
#1930000
1$
#1940000
0$
#1950000
1$
#1960000
0$
#1970000
1$
#1980000
0$
#1990000
1$
#2000000
0$
#2010000
1$
#2020000
0$
1#
#2030000
1$
#2040000
0$
0#
#2050000
1$
1'
b10100101 %
b10100101 (
#2060000
0$
#2070000
1$
#2080000
0$
#2090000
1$
#2100000
0$
#2110000
1$
#2120000
0$
#2130000
1$
#2140000
0$
#2150000
1$
#2160000
0$
#2170000
1$
#2180000
0$
#2190000
1$
#2200000
0$
#2210000
1$
#2220000
0$
#2230000
1$
#2240000
0$
#2250000
1$
#2260000
0$
#2270000
1$
#2280000
0$
#2290000
1$
#2300000
0$
#2310000
1$
#2320000
0$
#2330000
1$
#2340000
0$
#2350000
1$
#2360000
0$
#2370000
1$
#2380000
0$
#2390000
1$
#2400000
0$
#2410000
1$
#2420000
0$
#2430000
1$
#2440000
0$
#2450000
1$
#2460000
0$
#2470000
1$
#2480000
0$
#2490000
1$
#2500000
0$
#2510000
1$
#2520000
0$
#2530000
1$
#2540000
0$
#2550000
1$
#2560000
0$
#2570000
1$
#2580000
0$
#2590000
1$
#2600000
0$
#2610000
1$
#2620000
0$
#2630000
1$
#2640000
0$
#2650000
1$
#2660000
0$
#2670000
1$
#2680000
0$
#2690000
1$
#2700000
0$
#2710000
1$
#2720000
0$
#2730000
1$
#2740000
0$
#2750000
1$
#2760000
0$
#2770000
1$
#2780000
0$
#2790000
1$
#2800000
0$
#2810000
1$
#2820000
0$
#2830000
1$
#2840000
0$
#2850000
1$
#2860000
0$
#2870000
1$
#2880000
0$
#2890000
1$
#2900000
0$
#2910000
1$
#2920000
0$
#2930000
1$
#2940000
0$
#2950000
1$
#2960000
0$
#2970000
1$
#2980000
0$
#2990000
1$
#3000000
0$
#3010000
1$
#3020000
0$
#3030000
1$
#3040000
0$
1#
#3050000
b1 +
1$
#3060000
0$
0#
